fracjax/__init__.py
fracjax/api.py
fracjax/core/__init__.py
fracjax/core/preprocessing.py
fracjax/core/windowing.py
fracjax/estimators/__init__.py
fracjax/estimators/dfa.py
fracjax/estimators/entropy.py
fracjax/estimators/higuchi.py
fracjax/estimators/intermarket.py
fracjax/estimators/microstructure.py
fracjax/estimators/volatility.py
fracjax/estimators/wavelet.py
fracjax/math/__init__.py
fracjax/math/regression.py
fracjax/math/transforms.py
fracjax/utils/__init__.py
fracjax/utils/autotune.py
fracjax/utils/diagnostics.py
fracjax/utils/io.py
fracjax/utils/memory.py
fracjax/utils/progress.py
fracjax-0.1.1.dist-info/licenses/LICENSE
fracjax-0.1.1.dist-info/METADATA
fracjax-0.1.1.dist-info/WHEEL
fracjax-0.1.1.dist-info/top_level.txt
fracjax-0.1.1.dist-info/RECORD
