Metadata-Version: 2.4
Name: fracjax
Version: 0.1.1
Summary: High-Performance Fractal & Econophysics Tools for Financial Time Series using JAX (GPU-Accelerated)
Author-email: Mohammad Korivand <korivandmohammadb@gmail.com>
License: MIT License
Project-URL: Homepage, https://github.com/Mohamma0022/fracjax
Project-URL: Bug Tracker, https://github.com/Mohamma0022/fracjax/issues
Keywords: finance,fractal,jax,econophysics,hurst,wavelet,trading
Classifier: Programming Language :: Python :: 3
Classifier: License :: OSI Approved :: MIT License
Classifier: Operating System :: OS Independent
Classifier: Topic :: Office/Business :: Financial :: Investment
Classifier: Topic :: Scientific/Engineering :: Mathematics
Classifier: Intended Audience :: Financial and Insurance Industry
Classifier: Development Status :: 4 - Beta
Requires-Python: >=3.9
License-File: LICENSE
Requires-Dist: jax>=0.4.0
Requires-Dist: jaxlib>=0.4.0
Requires-Dist: numpy
Requires-Dist: pandas
Requires-Dist: scipy
Requires-Dist: tqdm
Dynamic: license-file
